[
  {
    "label": "Fit",
    "confidence": 0.997,
    "matched_skills": [
      "react",
      "html",
      "css",
      "express",
      "mongodb",
      "javascript",
      "node.js"
    ],
    "missing_skills": [],
    "feature_summary": {
      "skill_match_ratio": 1.0,
      "years_experience": 7,
      "test_score_norm": 0.78,
      "project_count": 3,
      "test_score_raw": 78
    },
    "explanation": "High test score (78/100) and covers most required skills (7/7 matched). Has strong portfolio (3 projects) and 7 years of solid experience. Model confidence: 1.00 \u2192 Fit.",
    "metadata": {
      "domain": "Web Development",
      "candidate_id": "candidate_1250",
      "classification_timestamp": "2025-10-09T22:45:46.719845",
      "model_version": "1.0"
    },
    "alternative_domain_suggestions": [
      {
        "rank": 1,
        "domain": "DevOps",
        "skill_match_ratio": 0.714,
        "matched_skills_count": 5,
        "required_skills_count": 7,
        "matched_skills": [
          "docker",
          "ci/cd",
          "kubernetes",
          "terraform",
          "aws"
        ],
        "key_missing_skills": [
          "jenkins",
          "linux"
        ]
      },
      {
        "rank": 2,
        "domain": "Cybersecurity",
        "skill_match_ratio": 0.429,
        "matched_skills_count": 3,
        "required_skills_count": 7,
        "matched_skills": [
          "python",
          "network security",
          "penetration testing"
        ],
        "key_missing_skills": [
          "encryption",
          "cissp",
          "firewall"
        ]
      },
      {
        "rank": 3,
        "domain": "Data Science",
        "skill_match_ratio": 0.286,
        "matched_skills_count": 2,
        "required_skills_count": 7,
        "matched_skills": [
          "python",
          "docker"
        ],
        "key_missing_skills": [
          "scikit-learn",
          "numpy",
          "pytorch"
        ]
      }
    ]
  },
  {
    "label": "Fit",
    "confidence": 0.955,
    "matched_skills": [
      "android",
      "java",
      "flutter",
      "kotlin",
      "ios",
      "swift",
      "react native"
    ],
    "missing_skills": [],
    "feature_summary": {
      "skill_match_ratio": 1.0,
      "years_experience": 5,
      "test_score_norm": 0.82,
      "project_count": 3,
      "test_score_raw": 82
    },
    "explanation": "High test score (82/100) and covers most required skills (7/7 matched). Has strong portfolio (3 projects) and 5 years of solid experience. Model confidence: 0.95 \u2192 Fit.",
    "metadata": {
      "domain": "Mobile Development",
      "candidate_id": "candidate_1251",
      "classification_timestamp": "2025-10-09T22:45:46.777851",
      "model_version": "1.0"
    },
    "alternative_domain_suggestions": [
      {
        "rank": 1,
        "domain": "DevOps",
        "skill_match_ratio": 0.429,
        "matched_skills_count": 3,
        "required_skills_count": 7,
        "matched_skills": [
          "docker",
          "aws",
          "terraform"
        ],
        "key_missing_skills": [
          "jenkins",
          "ci/cd",
          "kubernetes"
        ]
      },
      {
        "rank": 2,
        "domain": "Data Science",
        "skill_match_ratio": 0.286,
        "matched_skills_count": 2,
        "required_skills_count": 7,
        "matched_skills": [
          "python",
          "docker"
        ],
        "key_missing_skills": [
          "scikit-learn",
          "numpy",
          "pytorch"
        ]
      },
      {
        "rank": 3,
        "domain": "Cybersecurity",
        "skill_match_ratio": 0.143,
        "matched_skills_count": 1,
        "required_skills_count": 7,
        "matched_skills": [
          "python"
        ],
        "key_missing_skills": [
          "risk assessment",
          "encryption",
          "penetration testing"
        ]
      }
    ]
  },
  {
    "label": "Fit",
    "confidence": 0.995,
    "matched_skills": [
      "jenkins",
      "linux",
      "docker",
      "ci/cd",
      "kubernetes",
      "terraform",
      "aws"
    ],
    "missing_skills": [],
    "feature_summary": {
      "skill_match_ratio": 1.0,
      "years_experience": 8,
      "test_score_norm": 0.85,
      "project_count": 3,
      "test_score_raw": 85
    },
    "explanation": "Excellent test score (85/100) and covers most required skills (7/7 matched). Has strong portfolio (3 projects) and 8 years of solid experience. Model confidence: 0.99 \u2192 Fit.",
    "metadata": {
      "domain": "DevOps",
      "candidate_id": "candidate_1252",
      "classification_timestamp": "2025-10-09T22:45:46.833859",
      "model_version": "1.0"
    },
    "alternative_domain_suggestions": [
      {
        "rank": 1,
        "domain": "Data Science",
        "skill_match_ratio": 0.286,
        "matched_skills_count": 2,
        "required_skills_count": 7,
        "matched_skills": [
          "python",
          "docker"
        ],
        "key_missing_skills": [
          "scikit-learn",
          "numpy",
          "pytorch"
        ]
      },
      {
        "rank": 2,
        "domain": "Cybersecurity",
        "skill_match_ratio": 0.286,
        "matched_skills_count": 2,
        "required_skills_count": 7,
        "matched_skills": [
          "python",
          "penetration testing"
        ],
        "key_missing_skills": [
          "risk assessment",
          "encryption",
          "network security"
        ]
      },
      {
        "rank": 3,
        "domain": "Web Development",
        "skill_match_ratio": 0.143,
        "matched_skills_count": 1,
        "required_skills_count": 7,
        "matched_skills": [
          "node.js"
        ],
        "key_missing_skills": [
          "react",
          "html",
          "css"
        ]
      }
    ]
  },
  {
    "label": "Fit",
    "confidence": 0.882,
    "matched_skills": [
      "encryption",
      "python",
      "penetration testing",
      "network security",
      "firewall",
      "cissp"
    ],
    "missing_skills": [
      "risk assessment"
    ],
    "feature_summary": {
      "skill_match_ratio": 0.857,
      "years_experience": 6,
      "test_score_norm": 0.79,
      "project_count": 3,
      "test_score_raw": 79
    },
    "explanation": "High test score (79/100) and covers most required skills (6/7 matched), but lacks risk assessment. Has strong portfolio (3 projects) and 6 years of solid experience. Model confidence: 0.88 \u2192 Fit.",
    "metadata": {
      "domain": "Cybersecurity",
      "candidate_id": "candidate_1253",
      "classification_timestamp": "2025-10-09T22:45:46.888848",
      "model_version": "1.0"
    },
    "alternative_domain_suggestions": [
      {
        "rank": 1,
        "domain": "DevOps",
        "skill_match_ratio": 0.429,
        "matched_skills_count": 3,
        "required_skills_count": 7,
        "matched_skills": [
          "docker",
          "aws",
          "kubernetes"
        ],
        "key_missing_skills": [
          "jenkins",
          "ci/cd",
          "terraform"
        ]
      },
      {
        "rank": 2,
        "domain": "Data Science",
        "skill_match_ratio": 0.286,
        "matched_skills_count": 2,
        "required_skills_count": 7,
        "matched_skills": [
          "python",
          "docker"
        ],
        "key_missing_skills": [
          "scikit-learn",
          "numpy",
          "pytorch"
        ]
      },
      {
        "rank": 3,
        "domain": "Web Development",
        "skill_match_ratio": 0.0,
        "matched_skills_count": 0,
        "required_skills_count": 7,
        "matched_skills": [],
        "key_missing_skills": [
          "react",
          "html",
          "css"
        ]
      }
    ]
  },
  {
    "label": "Fit",
    "confidence": 0.971,
    "matched_skills": [
      "react",
      "html",
      "css",
      "express",
      "javascript",
      "node.js"
    ],
    "missing_skills": [
      "mongodb"
    ],
    "feature_summary": {
      "skill_match_ratio": 0.857,
      "years_experience": 5,
      "test_score_norm": 0.76,
      "project_count": 3,
      "test_score_raw": 76
    },
    "explanation": "High test score (76/100) and covers most required skills (6/7 matched), but lacks mongodb. Has strong portfolio (3 projects) and 5 years of solid experience. Model confidence: 0.97 \u2192 Fit.",
    "metadata": {
      "domain": "Web Development",
      "candidate_id": "candidate_1254",
      "classification_timestamp": "2025-10-09T22:45:46.947842",
      "model_version": "1.0"
    },
    "alternative_domain_suggestions": [
      {
        "rank": 1,
        "domain": "DevOps",
        "skill_match_ratio": 0.429,
        "matched_skills_count": 3,
        "required_skills_count": 7,
        "matched_skills": [
          "docker",
          "aws",
          "kubernetes"
        ],
        "key_missing_skills": [
          "jenkins",
          "ci/cd",
          "terraform"
        ]
      },
      {
        "rank": 2,
        "domain": "Data Science",
        "skill_match_ratio": 0.286,
        "matched_skills_count": 2,
        "required_skills_count": 7,
        "matched_skills": [
          "python",
          "docker"
        ],
        "key_missing_skills": [
          "scikit-learn",
          "numpy",
          "pytorch"
        ]
      },
      {
        "rank": 3,
        "domain": "Cybersecurity",
        "skill_match_ratio": 0.286,
        "matched_skills_count": 2,
        "required_skills_count": 7,
        "matched_skills": [
          "python",
          "penetration testing"
        ],
        "key_missing_skills": [
          "risk assessment",
          "encryption",
          "network security"
        ]
      }
    ]
  }
]